{
	"schemaVersion": 1,
	"id": "ever-j",
	"version": "0.1.2-Alpha",
	"name": "Ever-J",
	"description": "A unique mod in the JoJo's Blizzard Adventure universe with stands that you definitely haven't seen in other mods",
	"authors": [
		"Dov1ntc", "Captain_june"
	],
	"contact": {
		"sources": "https://github.com/dovintc-off/Ever-J-Minecraft-Mod-"
	},
	"license": "MIT",
	"icon": "assets/ever-j/icon.png",
	"environment": "*",
	"entrypoints": {
		"main": [
			"com.example.TemplateMod"
		],
		"client": [
			"com.example.TemplateModClient"
		]
	},
	"depends": {
		"fabricloader": ">=0.14.21",
		"minecraft": "~1.20.1",
		"java": ">=17",
		"fabric-api": "*",
		"cloth-config": ">=11.0.0"
	}
}